ncdu_dropbox/__init__.py
ncdu_dropbox/dirtree.py
ncdu_dropbox/dropboxfetcher.py
ncdu_dropbox/main.py
ncdu_dropbox/ncduwriter.py
ncdu_dropbox-0.1.dist-info/METADATA
ncdu_dropbox-0.1.dist-info/RECORD
ncdu_dropbox-0.1.dist-info/WHEEL
ncdu_dropbox-0.1.dist-info/entry_points.txt
ncdu_dropbox-0.1.dist-info/top_level.txt
