Metadata-Version: 2.1
Name: ncdu-dropbox
Version: 0.1
Summary: Generates ncdu compatible json file for Dropbox
Home-page: https://github.com/shitikanth/ncdu-dropbox
Author: Shitikanth Kashyap
Author-email: shitikanth1@gmail.com
License: MIT
Platform: UNKNOWN
Classifier: Development Status :: 3 - Alpha
Classifier: Intended Audience :: Developers
Classifier: License :: OSI Approved :: MIT License
Classifier: Operating System :: OS Independent
Classifier: Programming Language :: Python
Classifier: Programming Language :: Python :: 2.7
Classifier: Programming Language :: Python :: 3.6
Classifier: Topic :: Utilities
Requires-Dist: dropbox
